pdldb/__init__.py
pdldb/base_table_manager.py
pdldb/base_table_validator.py
pdldb/lake_manager.py
pdldb/local_table_manager.py
pdldb/s3_table_manager.py
pdldb-0.1.11.dist-info/METADATA
pdldb-0.1.11.dist-info/WHEEL
pdldb-0.1.11.dist-info/entry_points.txt
pdldb-0.1.11.dist-info/licenses/LICENSE
pdldb-0.1.11.dist-info/RECORD
