Metadata-Version: 2.4
Name: pdldb
Version: 0.1.11
Summary: A high-performance analytical data store combining Polars' processing speed with Delta Lake's ACID transactions. This lightweight wrapper provides a database-like experience for local and cloud based data processing.
Project-URL: Repository, https://github.com/0x6761746F/pdldb
Project-URL: Documentation, https://0x6761746f.github.io/pdldb/
Author-email: 0x6761746F <0x6761746F@0x6761746F.com>
License-Expression: Apache-2.0
License-File: LICENSE
Requires-Python: >=3.12.9
Requires-Dist: boto3>=1.35.90
Requires-Dist: deltalake>=0.25.4
Requires-Dist: polars>=1.26.0
Requires-Dist: pydantic>=2.10.6
